tablespoon/__init__.py
tablespoon/data.py
tablespoon/forecasters.py
tablespoon/model_selection.py
tablespoon-0.5.1.dist-info/LICENSE
tablespoon-0.5.1.dist-info/METADATA
tablespoon-0.5.1.dist-info/WHEEL
tablespoon-0.5.1.dist-info/RECORD
