Metadata-Version: 2.1
Name: tablespoon
Version: 0.5.1
Summary: Simple probabilistic time series benchmark models
Home-page: https://alexhallam.github.io/tablespoon/
License: MIT
Keywords: forecasting,forecast,probabilistic,naive,benchmark,seasonal naive,mean forecast
Author: Alex Hallam
Author-email: alexhallam6.28@gmail.com
Requires-Python: >=3.10
Classifier: License :: OSI Approved :: MIT License
Classifier: Programming Language :: Python :: 3
Classifier: Programming Language :: Python :: 3.10
Classifier: Programming Language :: Python :: 3.11
Requires-Dist: numpy (>=1.23.0,<2.0.0)
Requires-Dist: pandas (>=1.3.2,<2.0.0)
Requires-Dist: pytest (==7.0.0)
Requires-Dist: scipy (>=1.9.3,<2.0.0)
Requires-Dist: statsmodels (>=0.14.0,<0.15.0)
Project-URL: Repository, https://github.com/alexhallam/tablespoon
